pheromone_dispersion/__init__.py
pheromone_dispersion/__main__.py
pheromone_dispersion/advection_operator.py
pheromone_dispersion/cli.py
pheromone_dispersion/convection_diffusion_2D.py
pheromone_dispersion/deposition_coeff.py
pheromone_dispersion/diffusion_operator.py
pheromone_dispersion/diffusion_tensor.py
pheromone_dispersion/gaussian_plume.py
pheromone_dispersion/geom.py
pheromone_dispersion/identity_operator.py
pheromone_dispersion/reaction_operator.py
pheromone_dispersion/source_term.py
pheromone_dispersion/velocity.py
pherosensor/__init__.py
pherosensor/__main__.py
pherosensor/cli.py
source_localization/__init__.py
source_localization/adjoint_convection_diffusion_2D.py
source_localization/control.py
source_localization/cost.py
source_localization/gradient_descent.py
source_localization/obs.py
source_localization/population_dynamique.py
source_localization/proximal_gradient.py
utils/__init__.py
utils/generate_gif.py
utils/geom_to_shapefile.py
utils/plot_colormap.py
utils/plot_cost.py
utils/plot_ctrl.py
utils/plot_ctrl_error.py
utils/plot_env_param.py
utils/plot_obs.py
utils/superlevel_set.py
pherosensor-0.1.1.dist-info/AUTHORS.rst
pherosensor-0.1.1.dist-info/LICENSE
pherosensor-0.1.1.dist-info/METADATA
pherosensor-0.1.1.dist-info/WHEEL
pherosensor-0.1.1.dist-info/entry_points.txt
pherosensor-0.1.1.dist-info/top_level.txt
pherosensor-0.1.1.dist-info/RECORD
